noface/__init__.py
noface/noface.py
noface-1.5.0.dist-info/LICENSE.txt
noface-1.5.0.dist-info/METADATA
noface-1.5.0.dist-info/WHEEL
noface-1.5.0.dist-info/top_level.txt
noface-1.5.0.dist-info/RECORD
