Metadata-Version: 2.1
Name: noface
Version: 1.5.0
Summary: a cypher algo by Unproductive
Home-page: https://github.com/bgse/hellostackoverflow
Author: Unproductive Lab
Author-email: 107squad107@gmail.com
Keywords: noface,cypher,encoding
Classifier: Programming Language :: Python :: 3.11
License-File: LICENSE.txt
